comandor/__init__.py
comandor/app.py
comandor/args.py
comandor/errors.py
comandor/log.py
comandor/main.py
comandor/models.py
comandor/settings.py
comandor-0.4.1.dist-info/LICENSE
comandor-0.4.1.dist-info/METADATA
comandor-0.4.1.dist-info/WHEEL
comandor-0.4.1.dist-info/entry_points.txt
comandor-0.4.1.dist-info/top_level.txt
comandor-0.4.1.dist-info/RECORD
