Metadata-Version: 2.1
Name: comandor
Version: 0.4.1
Summary: A Very Simple Script for Run your command!
Home-page: https://github.com/NoobforAl/comandor
Author: NoobforAl
Author-email: FarshadSarmali@pm.me
License: MIT License
Keywords: command line,script
Classifier: Development Status :: 1 - Planning
Classifier: Intended Audience :: Science/Research
Classifier: License :: OSI Approved :: BSD License
Classifier: License :: OSI Approved :: MIT License
Classifier: Operating System :: OS Independent
Classifier: Programming Language :: Python :: 3
License-File: LICENSE
Requires-Dist: pydantic (>=1.10.5)
Requires-Dist: tqdm (>=4.65.0)
Requires-Dist: PyYaml (>=6.0.1)
